ciman/__main__.py
ciman/jsonrules.py
ciman/pull.py
ciman/registry.py
ciman/version.py
ciman/view/info.py
tests/test_version.py
ciman-0.0.5.dist-info/LICENSE
ciman-0.0.5.dist-info/METADATA
ciman-0.0.5.dist-info/WHEEL
ciman-0.0.5.dist-info/entry_points.txt
ciman-0.0.5.dist-info/top_level.txt
ciman-0.0.5.dist-info/RECORD
