Metadata-Version: 2.1
Name: ciman
Version: 0.0.5
Summary: Container image management Python library and client
Home-page: https://github.com/joaompinto/ciman
Author: João Pinto
Author-email: lamego.pinto@gmail.com
License: MIT
Platform: UNKNOWN
License-File: LICENSE
Requires-Dist: httpx
Requires-Dist: rich
Requires-Dist: typer
